{
    "matiers": [
        {
            "name": "Maths",
            "description": "On sait depuis longtemps que travailler avec du text lisible etlongtemps que travailler avec du text lisible etF"
        },{
            "name": "Physique",
            "description": "On sait depuis longtemps que travailler avec du text lisible etlongtemps que travailler avec du text lisible etF"
        },{
            "name": "SVT",
            "description": "On sait depuis longtemps que travailler avec du text lisible etlongtemps que travailler avec du text lisible etF"
        },{
            "name": "Arabe",
            "description": "On sait depuis longtemps que travailler avec du text lisible etlongtemps que travailler avec du text lisible etF"
        },{
            "name": "Anglais",
            "description": "On sait depuis longtemps que travailler avec du text lisible etlongtemps que travailler avec du text lisible etF"
        },{
            "name": "Maths",
            "description": "On sait depuis longtemps que travailler avec du text lisible etlongtemps que travailler avec du text lisible etF"
        },{
            "name": "Physique",
            "description": "On sait depuis longtemps que travailler avec du text lisible etlongtemps que travailler avec du text lisible etF"
        }
    ]
}